{
  "id": 1896476,
  "state": "WA",
  "state_name": "Washington",
  "bill_number": "HB1052",
  "title": "Clarifying a hate crime offense.",
  "summary": "Clarifying a hate crime offense.",
  "status": "signed_into_law",
  "status_label": "Passed",
  "status_code": 4,
  "categories": [
    "other"
  ],
  "primary_category": "other",
  "level": "state",
  "last_action_date": "",
  "last_action": "",
  "url": "https://legiscan.com/WA/bill/HB1052/2025",
  "legiscan_url": "https://legiscan.com/WA/bill/HB1052/2025",
  "state_url": "https://app.leg.wa.gov/billsummary?BillNumber=1052&Year=2025&Initiative=false",
  "sponsors": [
    "Cindy Ryu (D) [Rep]",
    "Alex Ramel (D) [Rep]",
    "Mari Leavitt (D) [Rep]",
    "Liz Berry (D) [Rep]",
    "Jamila Taylor (D) [Rep]",
    "Julia Reed (D) [Rep]",
    "My-Linh Thai (D) [Rep]",
    "Edwin Obras (D) [Rep]",
    "Nicole Macri (D) [Rep]",
    "Julio Cortes (D) [Rep]",
    "Lisa Callan (D) [Rep]",
    "Lisa Parshley (D) [Rep]",
    "Mary Fosse (D) [Rep]",
    "Mia Gregerson (D) [Rep]",
    "Roger Goodman (D) [Rep]",
    "Gerry Pollet (D) [Rep]",
    "Shelley Kloba (D) [Rep]",
    "April Berg (D) [Rep]",
    "Lauren Davis (D) [Rep]",
    "Timm Ormsby (D) [Rep]",
    "Osman Salahuddin (D) [Rep]",
    "Kristine Reeves (D) [Rep]",
    "Natasha Hill (D) [Rep]"
  ],
  "introduced_date": "2025-05-12",
  "session": "2025-2026 Regular Session",
  "actions": [
    {
      "date": "2024-12-12",
      "action": "Prefiled for introduction.",
      "chamber": "H"
    },
    {
      "date": "2025-01-13",
      "action": "First reading, referred to Community Safety.",
      "chamber": "H"
    },
    {
      "date": "2025-01-13",
      "action": "Public hearing in the House Committee on Community Safety at 2:00 PM.",
      "chamber": "H"
    },
    {
      "date": "2025-01-16",
      "action": "Executive action taken in the House Committee on Community Safety at 8:30 AM.",
      "chamber": "H"
    },
    {
      "date": "2025-01-16",
      "action": "CS - Majority; do pass.",
      "chamber": "H"
    },
    {
      "date": "2025-01-16",
      "action": "Minority; without recommendation.",
      "chamber": "H"
    },
    {
      "date": "2025-01-17",
      "action": "Referred to Rules 2 Review.",
      "chamber": "H"
    },
    {
      "date": "2025-02-11",
      "action": "Rules Committee relieved of further consideration. Placed on second reading.",
      "chamber": "H"
    },
    {
      "date": "2025-02-13",
      "action": "Floor amendment",
      "chamber": "H"
    },
    {
      "date": "2025-02-13",
      "action": "Rules suspended. Placed on Third Reading.",
      "chamber": "H"
    },
    {
      "date": "2025-02-13",
      "action": "Third reading, passed; yeas, 61; nays, 31; absent, 0; excused, 6.",
      "chamber": "H"
    },
    {
      "date": "2025-02-17",
      "action": "First reading, referred to Law & Justice.",
      "chamber": "S"
    },
    {
      "date": "2025-03-13",
      "action": "Public hearing in the Senate Committee on Law & Justice at 10:30 AM.",
      "chamber": "S"
    },
    {
      "date": "2025-03-20",
      "action": "Executive action taken in the Senate Committee on Law & Justice at 10:30 AM.",
      "chamber": "S"
    },
    {
      "date": "2025-03-20",
      "action": "LAW - Majority; do pass with amendment",
      "chamber": "S"
    },
    {
      "date": "2025-03-20",
      "action": "Minority; do not pass.",
      "chamber": "S"
    },
    {
      "date": "2025-03-24",
      "action": "Passed to Rules Committee for second reading.",
      "chamber": "S"
    },
    {
      "date": "2025-03-26",
      "action": "Placed on second reading by Rules Committee.",
      "chamber": "S"
    },
    {
      "date": "2025-04-03",
      "action": "Committee amendment",
      "chamber": "S"
    },
    {
      "date": "2025-04-03",
      "action": "Rules suspended. Placed on Third Reading.",
      "chamber": "S"
    },
    {
      "date": "2025-04-03",
      "action": "Third reading, passed; yeas, 30; nays, 19; absent, 0; excused, 0.",
      "chamber": "S"
    },
    {
      "date": "2025-04-18",
      "action": "House concurred in Senate amendments.",
      "chamber": "H"
    },
    {
      "date": "2025-04-18",
      "action": "Passed final passage; yeas, 59; nays, 38; absent, 0; excused, 1.",
      "chamber": "H"
    },
    {
      "date": "2025-04-18",
      "action": "Speaker signed.",
      "chamber": "H"
    },
    {
      "date": "2025-04-19",
      "action": "President signed.",
      "chamber": "S"
    },
    {
      "date": "2025-04-22",
      "action": "Delivered to Governor.",
      "chamber": "H"
    },
    {
      "date": "2025-05-12",
      "action": "Governor signed.",
      "chamber": "H"
    },
    {
      "date": "2025-05-12",
      "action": "Chapter 249, 2025 Laws.",
      "chamber": "H"
    },
    {
      "date": "2025-05-12",
      "action": "Effective date 7/27/2025.",
      "chamber": "H"
    }
  ],
  "votes": [
    {
      "date": "2025-01-16",
      "description": "House Committee on Community Safety: do pass",
      "yea": 5,
      "nay": 0,
      "passed": 1
    },
    {
      "date": "2025-02-13",
      "description": "House 3rd Reading & Final Passage",
      "yea": 61,
      "nay": 31,
      "passed": 1
    },
    {
      "date": "2025-03-20",
      "description": "Senate Committee on Law & Justice: do pass with amendment(s)",
      "yea": 5,
      "nay": 4,
      "passed": 1
    },
    {
      "date": "2025-04-03",
      "description": "Senate 3rd Reading & Final Passage as Amended by the Senate",
      "yea": 30,
      "nay": 19,
      "passed": 1
    },
    {
      "date": "2025-04-18",
      "description": "House Final Passage as Amended by the Senate",
      "yea": 59,
      "nay": 38,
      "passed": 1
    }
  ],
  "texts": [
    {
      "date": "2024-12-12",
      "type": "Introduced",
      "url": "https://lawfilesext.leg.wa.gov/biennium/2025-26/Pdf/Bills/House%20Bills/1052.pdf",
      "doc_id": 3032910
    },
    {
      "date": "0000-00-00",
      "type": "Engrossed",
      "url": "https://lawfilesext.leg.wa.gov/biennium/2025-26/Pdf/Bills/House%20Bills/1052.E.pdf",
      "doc_id": 3120101
    },
    {
      "date": "0000-00-00",
      "type": "Enrolled",
      "url": "https://lawfilesext.leg.wa.gov/biennium/2025-26/Pdf/Bills/House%20Passed%20Legislature/1052.PL.pdf",
      "doc_id": 3216059
    },
    {
      "date": "0000-00-00",
      "type": "Chaptered",
      "url": "https://lawfilesext.leg.wa.gov/biennium/2025-26/Pdf/Bills/Session%20Laws/House/1052.SL.pdf",
      "doc_id": 3238985
    }
  ],
  "committee": [],
  "subjects": []
}