{
  "id": 2002653,
  "state": "MA",
  "state_name": "Massachusetts",
  "bill_number": "H218",
  "title": "Resolve establishing the Harmony commission to study and make recommendations related to the welfare and best interests of children in care and protection cases",
  "summary": "For legislation to establish the harmony commission to study the welfare of children in care and protection cases. Children, Families and Persons with Disabilities.",
  "status": "introduced",
  "status_label": "Introduced",
  "status_code": 1,
  "categories": [
    "education"
  ],
  "primary_category": "education",
  "level": "state",
  "last_action_date": "",
  "last_action": "",
  "url": "https://legiscan.com/MA/bill/H218/2025",
  "legiscan_url": "https://legiscan.com/MA/bill/H218/2025",
  "state_url": "https://malegislature.gov/Bills/194/H218",
  "sponsors": [
    "Carol Doherty (D) [Rep]"
  ],
  "introduced_date": "2025-02-27",
  "session": "194th General Court",
  "actions": [
    {
      "date": "2025-02-27",
      "action": "Referred to the Joint Committee on Children, Families and Persons with Disabilities",
      "chamber": "H"
    },
    {
      "date": "2025-02-27",
      "action": "Senate concurred",
      "chamber": "S"
    },
    {
      "date": "2025-07-11",
      "action": "Hearing scheduled for 07/22/2025 from 01:00 PM-05:00 PM in A-1",
      "chamber": "J"
    },
    {
      "date": "2025-07-22",
      "action": "Hearing rescheduled to 07/22/2025 from 01:00 PM-03:15 PM in A-1 and Virtual Hearing updated to New End Time",
      "chamber": "J"
    },
    {
      "date": "2025-12-31",
      "action": "Accompanied a study order, see H4883",
      "chamber": "H"
    }
  ],
  "votes": [],
  "texts": [
    {
      "date": "2025-02-27",
      "type": "Introduced",
      "url": "https://malegislature.gov/Bills/194/H218.pdf",
      "doc_id": 3168709
    }
  ],
  "committee": [],
  "subjects": []
}