{
  "id": 2002505,
  "state": "MA",
  "state_name": "Massachusetts",
  "bill_number": "H740",
  "title": "Relative to school mascot name changes",
  "summary": "Relative to school mascot name changes. Education.",
  "status": "introduced",
  "status_label": "Introduced",
  "status_code": 1,
  "categories": [
    "education"
  ],
  "primary_category": "education",
  "level": "state",
  "last_action_date": "",
  "last_action": "",
  "url": "https://legiscan.com/MA/bill/H740/2025",
  "legiscan_url": "https://legiscan.com/MA/bill/H740/2025",
  "state_url": "https://malegislature.gov/Bills/194/H740",
  "sponsors": [
    "Marcus Vaughn (R) [Rep]"
  ],
  "introduced_date": "2025-02-27",
  "session": "194th General Court",
  "actions": [
    {
      "date": "2025-02-27",
      "action": "Referred to the Joint Committee on Education",
      "chamber": "H"
    },
    {
      "date": "2025-02-27",
      "action": "Senate concurred",
      "chamber": "S"
    },
    {
      "date": "2025-06-06",
      "action": "Hearing scheduled for 06/17/2025 from 01:00 PM-05:00 PM in B-2",
      "chamber": "J"
    }
  ],
  "votes": [],
  "texts": [
    {
      "date": "2025-02-27",
      "type": "Introduced",
      "url": "https://malegislature.gov/Bills/194/H740.pdf",
      "doc_id": 3168555
    }
  ],
  "committee": {
    "committee_id": 757,
    "chamber": "J",
    "chamber_id": 103,
    "name": "Education"
  },
  "subjects": []
}