{
  "id": 2007691,
  "state": "TX",
  "state_name": "Texas",
  "bill_number": "SB2920",
  "title": "Relating to the regulation of steroid use by students participating in athletic competitions sponsored or sanctioned by the University Interscholastic League.",
  "summary": "Relating to the regulation of steroid use by students participating in athletic competitions sponsored or sanctioned by the University Interscholastic League.",
  "status": "passed_one_chamber",
  "status_label": "Engrossed",
  "status_code": 2,
  "categories": [
    "sports",
    "education"
  ],
  "primary_category": "sports",
  "level": "state",
  "last_action_date": "",
  "last_action": "",
  "url": "https://legiscan.com/TX/bill/SB2920/2025",
  "legiscan_url": "https://legiscan.com/TX/bill/SB2920/2025",
  "state_url": "https://capitol.texas.gov/BillLookup/History.aspx?LegSess=89R&Bill=SB2920",
  "sponsors": [
    "Donna Campbell (R) [Sen]",
    "Charles Creighton (R) [Sen]",
    "Bob Hall (R) [Sen]",
    "Shelby Slawson (R) [Rep]"
  ],
  "introduced_date": "2025-04-29",
  "session": "89th Legislature Regular Session",
  "actions": [
    {
      "date": "2025-03-14",
      "action": "Received by the Secretary of the Senate",
      "chamber": "S"
    },
    {
      "date": "2025-03-14",
      "action": "Filed",
      "chamber": "S"
    },
    {
      "date": "2025-04-07",
      "action": "Read first time",
      "chamber": "S"
    },
    {
      "date": "2025-04-07",
      "action": "Referred to Education K-16",
      "chamber": "S"
    },
    {
      "date": "2025-04-15",
      "action": "Scheduled for public hearing on . . .",
      "chamber": "S"
    },
    {
      "date": "2025-04-15",
      "action": "Considered in public hearing",
      "chamber": "S"
    },
    {
      "date": "2025-04-15",
      "action": "Left pending in committee",
      "chamber": "S"
    },
    {
      "date": "2025-04-16",
      "action": "Considered in public hearing",
      "chamber": "S"
    },
    {
      "date": "2025-04-16",
      "action": "Vote taken in committee",
      "chamber": "S"
    },
    {
      "date": "2025-04-22",
      "action": "Reported favorably w/o amendments",
      "chamber": "S"
    },
    {
      "date": "2025-04-22",
      "action": "Committee report printed and distributed",
      "chamber": "S"
    },
    {
      "date": "2025-04-23",
      "action": "Placed on intent calendar",
      "chamber": "S"
    },
    {
      "date": "2025-04-29",
      "action": "Co-author authorized",
      "chamber": "S"
    },
    {
      "date": "2025-04-29",
      "action": "Rules suspended-Regular order of business",
      "chamber": "S"
    },
    {
      "date": "2025-04-29",
      "action": "Record vote",
      "chamber": "S"
    },
    {
      "date": "2025-04-29",
      "action": "Read 2nd time & passed to engrossment",
      "chamber": "S"
    },
    {
      "date": "2025-04-29",
      "action": "Record vote",
      "chamber": "S"
    },
    {
      "date": "2025-04-29",
      "action": "Three day rule suspended",
      "chamber": "S"
    },
    {
      "date": "2025-04-29",
      "action": "Record vote",
      "chamber": "S"
    },
    {
      "date": "2025-04-29",
      "action": "Read 3rd time",
      "chamber": "S"
    },
    {
      "date": "2025-04-29",
      "action": "Passed",
      "chamber": "S"
    },
    {
      "date": "2025-04-29",
      "action": "Record vote",
      "chamber": "S"
    },
    {
      "date": "2025-04-29",
      "action": "Reported engrossed",
      "chamber": "S"
    },
    {
      "date": "2025-04-29",
      "action": "Received from the Senate",
      "chamber": "H"
    },
    {
      "date": "2025-04-30",
      "action": "Read first time",
      "chamber": "H"
    },
    {
      "date": "2025-04-30",
      "action": "Referred to Public Education",
      "chamber": "H"
    },
    {
      "date": "2025-05-12",
      "action": "Posting rule suspended",
      "chamber": "H"
    },
    {
      "date": "2025-05-13",
      "action": "Scheduled for public hearing on . . .",
      "chamber": "S"
    },
    {
      "date": "2025-05-13",
      "action": "No action taken in committee",
      "chamber": "H"
    },
    {
      "date": "2025-05-14",
      "action": "Posting rule suspended",
      "chamber": "H"
    },
    {
      "date": "2025-05-15",
      "action": "Scheduled for public hearing on . . .",
      "chamber": "H"
    },
    {
      "date": "2025-05-15",
      "action": "Considered in public hearing",
      "chamber": "H"
    },
    {
      "date": "2025-05-15",
      "action": "Testimony taken/registration(s) recorded in committee",
      "chamber": "H"
    },
    {
      "date": "2025-05-15",
      "action": "Left pending in committee",
      "chamber": "H"
    },
    {
      "date": "2025-05-16",
      "action": "Considered in formal meeting",
      "chamber": "H"
    },
    {
      "date": "2025-05-16",
      "action": "Reported favorably w/o amendment(s)",
      "chamber": "H"
    },
    {
      "date": "2025-05-20",
      "action": "Comte report filed with Committee Coordinator",
      "chamber": "H"
    },
    {
      "date": "2025-05-20",
      "action": "Committee report distributed",
      "chamber": "H"
    },
    {
      "date": "2025-05-21",
      "action": "Committee report sent to Calendars",
      "chamber": "H"
    },
    {
      "date": "2025-05-23",
      "action": "Considered in Calendars",
      "chamber": "H"
    },
    {
      "date": "2025-05-25",
      "action": "Placed on General State Calendar",
      "chamber": "H"
    },
    {
      "date": "2025-05-27",
      "action": "Read 2nd time",
      "chamber": "H"
    },
    {
      "date": "2025-05-27",
      "action": "Point of order withdrawn Rule 8, Section 1(a)(1)",
      "chamber": "H"
    },
    {
      "date": "2025-05-27",
      "action": "Postponed 6/3/25 10:00 AM",
      "chamber": "H"
    }
  ],
  "votes": [
    {
      "date": "2025-04-29",
      "description": "Rules suspended-Regular order of business",
      "yea": 27,
      "nay": 4,
      "passed": 1
    },
    {
      "date": "2025-04-29",
      "description": "Read 2nd time & passed to engrossment",
      "yea": 27,
      "nay": 4,
      "passed": 1
    },
    {
      "date": "2025-04-29",
      "description": "Three day rule suspended",
      "yea": 25,
      "nay": 6,
      "passed": 1
    },
    {
      "date": "2025-04-29",
      "description": "Read 3rd time",
      "yea": 0,
      "nay": 1,
      "passed": 0
    }
  ],
  "texts": [
    {
      "date": "2025-03-14",
      "type": "Introduced",
      "url": "https://capitol.texas.gov/tlodocs/89R/billtext/html/SB02920I.htm",
      "doc_id": 3175383
    },
    {
      "date": "2025-04-22",
      "type": "Comm Sub",
      "url": "https://capitol.texas.gov/tlodocs/89R/billtext/html/SB02920S.htm",
      "doc_id": 3218077
    },
    {
      "date": "2025-04-29",
      "type": "Engrossed",
      "url": "https://capitol.texas.gov/tlodocs/89R/billtext/html/SB02920E.htm",
      "doc_id": 3224579
    },
    {
      "date": "2025-05-20",
      "type": "Comm Sub",
      "url": "https://capitol.texas.gov/tlodocs/89R/billtext/html/SB02920H.htm",
      "doc_id": 3241220
    }
  ],
  "committee": [],
  "subjects": [
    "Education",
    "Education--Primary & Secondary",
    "Education--Primary & Secondary--Extracurricular Activities",
    "Minors",
    "Minors--Health & Safety",
    "GENDER IDENTITY & EXPRESSION",
    "MEDICINE & PRESCRIPTION DRUGS"
  ]
}