{
  "id": 2026308,
  "state": "PA",
  "state_name": "Pennsylvania",
  "bill_number": "HB1314",
  "title": "Establishing the Compassionate Name Change Assistance Grant Program and the Compassionate Name Change Assistance Grant Fund; and making an interfund transfer.",
  "summary": "An Act amending Title 54 (Names) of the Pennsylvania Consolidated Statutes, establishing the Compassionate Name Change Assistance Grant Program and the Compassionate Name Change Assistance Grant Fund; and making an interfund transfer.",
  "status": "introduced",
  "status_label": "Introduced",
  "status_code": 1,
  "categories": [
    "other"
  ],
  "primary_category": "other",
  "level": "state",
  "last_action_date": "",
  "last_action": "",
  "url": "https://legiscan.com/PA/bill/HB1314/2025",
  "legiscan_url": "https://legiscan.com/PA/bill/HB1314/2025",
  "state_url": "https://www.palegis.us/legislation/bills/2025/hb1314",
  "sponsors": [
    "Ben Sanchez (D) [Rep]",
    "Melissa Shusterman (D) [Rep]",
    "Ismail Smith-Wade-El (D) [Rep]",
    "Carol Hill-Evans (D) [Rep]",
    "Joshua Siegel (D) [Rep]",
    "Benjamin Waxman (D) [Rep]",
    "Joseph Hohenstein (D) [Rep]",
    "Christopher Rabb (D) [Rep]",
    "Dan Frankel (D) [Rep]",
    "Johanny Cepeda-Freytiz (D) [Rep]",
    "Nancy Guenst (D) [Rep]",
    "Dan Williams (D) [Rep]",
    "La'Tasha Mayes (D) [Rep]",
    "David Delloso (D) [Rep]",
    "Nikki Rivera (D) [Rep]",
    "Steven Malagari (D) [Rep]"
  ],
  "introduced_date": "2025-04-28",
  "session": "2025-2026 Regular Session",
  "actions": [
    {
      "date": "2025-04-28",
      "action": "Referred to Judiciary",
      "chamber": "H"
    }
  ],
  "votes": [],
  "texts": [
    {
      "date": "0000-00-00",
      "type": "Introduced",
      "url": "https://www.palegis.us/legislation/bills/text/PDF/2025/0/HB1314/PN1507",
      "doc_id": 3223412
    }
  ],
  "committee": {
    "committee_id": 53,
    "chamber": "H",
    "chamber_id": 3,
    "name": "Judiciary"
  },
  "subjects": []
}