{
  "id": 2038425,
  "state": "US",
  "state_name": "Federal",
  "bill_number": "HR549",
  "title": "Expressing support for the designation of June 26 as \"LGBTQI+ Equality Day\".",
  "summary": "Expressing support for the designation of June 26 as \"LGBTQI+ Equality Day\".",
  "status": "introduced",
  "status_label": "Introduced",
  "status_code": 1,
  "categories": [
    "other"
  ],
  "primary_category": "other",
  "level": "federal",
  "last_action_date": "",
  "last_action": "",
  "url": "https://legiscan.com/US/bill/HR549/2025",
  "legiscan_url": "https://legiscan.com/US/bill/HR549/2025",
  "state_url": "https://www.congress.gov/bill/119th-congress/house-resolution/549/all-info",
  "sponsors": [
    "Suzan DelBene (D) [Rep]",
    "Joyce Beatty (D) [Rep]",
    "Stephen Lynch (D) [Rep]",
    "Eleanor Norton (D) [Rep]",
    "Scott Peters (D) [Rep]",
    "Jared Huffman (D) [Rep]",
    "Kevin Mullin (D) [Rep]",
    "Mary Gay Scanlon (D) [Rep]",
    "Teresa Fernandez (D) [Rep]",
    "Chellie Pingree (D) [Rep]",
    "Henry Johnson (D) [Rep]",
    "Ritchie Torres (D) [Rep]",
    "Jill Tokuda (D) [Rep]",
    "Julia Brownley (D) [Rep]",
    "Sharice Davids (D) [Rep]",
    "Mike Quigley (D) [Rep]",
    "Jimmy Panetta (D) [Rep]",
    "Salud Carbajal (D) [Rep]",
    "Mark Takano (D) [Rep]",
    "Rashida Tlaib (D) [Rep]",
    "Morgan McGarvey (D) [Rep]",
    "Janice Schakowsky (D) [Rep]",
    "Dwight Evans (D) [Rep]",
    "Madeleine Dean (D) [Rep]",
    "James McGovern (D) [Rep]",
    "Raja Krishnamoorthi (D) [Rep]",
    "Diana DeGette (D) [Rep]",
    "Julie Johnson (D) [Rep]",
    "Nikema Williams (D) [Rep]",
    "Joseph Morelle (D) [Rep]",
    "Ed Case (D) [Rep]",
    "Dina Titus (D) [Rep]",
    "Paul Tonko (D) [Rep]",
    "LaMonica McIver (D) [Rep]",
    "Sarah McBride (D) [Rep]",
    "John Garamendi (D) [Rep]",
    "Bonnie Coleman (D) [Rep]",
    "Robert Menendez (D) [Rep]",
    "Jesus Garcia (D) [Rep]",
    "James Himes (D) [Rep]",
    "Frank Pallone (D) [Rep]",
    "Linda Sanchez (D) [Rep]",
    "William Keating (D) [Rep]",
    "Valerie Foushee (D) [Rep]",
    "Jasmine Crockett (D) [Rep]",
    "Mark Pocan (D) [Rep]",
    "Lateefah Simon (D) [Rep]",
    "Nydia Velazquez (D) [Rep]",
    "Troy Carter (D) [Rep]",
    "Bradley Schneider (D) [Rep]",
    "Sydney Kamlager-Dove (D) [Rep]",
    "Shri Thanedar (D) [Rep]",
    "Suzanne Bonamici (D) [Rep]",
    "Ami Bera (D) [Rep]",
    "Richard Neal (D) [Rep]",
    "Derek Tran (D) [Rep]",
    "Emanuel Cleaver (D) [Rep]",
    "Timothy Kennedy (D) [Rep]",
    "Shontel Brown (D) [Rep]",
    "Maxine Dexter (D) [Rep]",
    "Pramila Jayapal (D) [Rep]",
    "Rosa DeLauro (D) [Rep]",
    "Gwen Moore (D) [Rep]",
    "Danny Davis (D) [Rep]",
    "Nanette Barragan (D) [Rep]",
    "Ted Lieu (D) [Rep]",
    "Betty McCollum (D) [Rep]",
    "Val Hoyle (D) [Rep]",
    "Hillary Scholten (D) [Rep]",
    "Christopher Deluzio (D) [Rep]",
    "Adam Smith (D) [Rep]",
    "Bill Foster (D) [Rep]",
    "Elizabeth Fletcher (D) [Rep]",
    "Jennifer McClellan (D) [Rep]",
    "Judy Chu (D) [Rep]",
    "Frederica Wilson (D) [Rep]",
    "Robert Garcia (D) [Rep]",
    "Angela Craig (D) [Rep]",
    "George Latimer (D) [Rep]",
    "Nikki Budzinski (D) [Rep]",
    "Darren Soto (D) [Rep]",
    "Sylvia Garcia (D) [Rep]",
    "Becca Balint (D) [Rep]",
    "Debbie Wasserman Schultz (D) [Rep]",
    "Haley Stevens (D) [Rep]",
    "Joe Courtney (D) [Rep]",
    "Terri Sewell (D) [Rep]",
    "Robert Scott (D) [Rep]",
    "Jonathan Jackson (D) [Rep]",
    "Andre Carson (D) [Rep]",
    "Luz Rivas (D) [Rep]",
    "Alexandria Ocasio-Cortez (D) [Rep]",
    "Emily Randall (D) [Rep]",
    "Greg Landsman (D) [Rep]",
    "Seth Magaziner (D) [Rep]"
  ],
  "introduced_date": "2025-06-26",
  "session": "119th Congress",
  "actions": [
    {
      "date": "2025-06-26",
      "action": "Submitted in House",
      "chamber": "H"
    },
    {
      "date": "2025-06-26",
      "action": "Referred to the House Committee on the Judiciary.",
      "chamber": "H"
    }
  ],
  "votes": [],
  "texts": [
    {
      "date": "2025-06-27",
      "type": "Introduced",
      "url": "https://www.congress.gov/119/bills/hres549/BILLS-119hres549ih.pdf",
      "doc_id": 3259319
    }
  ],
  "committee": {
    "committee_id": 2309,
    "chamber": "H",
    "chamber_id": 114,
    "name": "Judiciary"
  },
  "subjects": [
    "Civil rights and liberties, minority issues"
  ]
}