{
  "id": 2087090,
  "state": "HI",
  "state_name": "Hawaii",
  "bill_number": "HB1628",
  "title": "Relating To Compassionate Release.",
  "summary": "Establishes a protocol for compassionate release for certain ill or seriously debilitated incarcerated persons. Establishes a working group within the Department of Corrections and Rehabilitation to develop initial administrative rules to implement the protocol. Effective 7/1/3000. (HD2)",
  "status": "passed_one_chamber",
  "status_label": "Engrossed",
  "status_code": 2,
  "categories": [
    "other"
  ],
  "primary_category": "other",
  "level": "state",
  "last_action_date": "",
  "last_action": "",
  "url": "https://legiscan.com/HI/bill/HB1628/2026",
  "legiscan_url": "https://legiscan.com/HI/bill/HB1628/2026",
  "state_url": "https://www.capitol.hawaii.gov/session/measure_indiv.aspx?billtype=HB&billnumber=1628&year=2026",
  "sponsors": [
    "David Tarnas (D) [Rep]",
    "Terez Amato (D) [Rep]",
    "Della au Belatti (D) [Rep]",
    "Luke Evslin (D) [Rep]",
    "Tina Grandinetti (D) [Rep]",
    "Ikaika Hussey (D) [Rep]",
    "Greggor Ilagan (D) [Rep]",
    "Kim Iwamoto (D) [Rep]",
    "Lisa Marten (D) [Rep]",
    "Daynette Morikawa (D) [Rep]",
    "Ikaika Olds (D) [Rep]",
    "Amy Perruso (D) [Rep]",
    "Mahina Poepoe (D) [Rep]",
    "Julie Reyes Oda (R) [Rep]",
    "Kanani Souza (R) [Rep]",
    "Gregg Takayama (D) [Rep]"
  ],
  "introduced_date": "2026-03-10",
  "session": "2026 Regular Session",
  "actions": [
    {
      "date": "2026-01-20",
      "action": "Prefiled.",
      "chamber": "H"
    },
    {
      "date": "2026-01-21",
      "action": "Introduced and Pass First Reading.",
      "chamber": "H"
    },
    {
      "date": "2026-01-26",
      "action": "Referred to PBS, JHA, referral sheet 1",
      "chamber": "H"
    },
    {
      "date": "2026-01-30",
      "action": "Bill scheduled to be heard by PBS on Wednesday, 02-04-26 9:00AM in House conference room 411 VIA VIDEOCONFERENCE.",
      "chamber": "H"
    },
    {
      "date": "2026-02-04",
      "action": "The committee(s) on PBS recommend(s) that the measure be deferred until 02-11-26, 11:30AM.",
      "chamber": "H"
    },
    {
      "date": "2026-02-05",
      "action": "Bill scheduled for decision making on Wednesday, 02-11-26 11:30AM in conference room 411 VIA VIDEOCONFERENCE.",
      "chamber": "H"
    },
    {
      "date": "2026-02-11",
      "action": "The committee on PBS recommend that the measure be PASSED, WITH AMENDMENTS. The votes were as follows: 9 Ayes: Representative(s) Belatti, Iwamoto, Hashem, Ichiyama, Morikawa, Poepoe, Woodson, Shimizu, Souza; Ayes with reservations: none; Noes: none; and Excused: none.",
      "chamber": "H"
    },
    {
      "date": "2026-02-20",
      "action": "Reported from PBS (Stand. Com. Rep. No. 600-26) as amended in HD 1, recommending passage on Second Reading and referral to JHA.",
      "chamber": "H"
    },
    {
      "date": "2026-02-20",
      "action": "Passed Second Reading as amended in HD 1 and referred to the committee(s) on JHA with none voting aye with reservations; Representative(s) Pierick voting no (1) and Representative(s) Quinlan excused (1).",
      "chamber": "H"
    },
    {
      "date": "2026-02-23",
      "action": "Bill scheduled to be heard by JHA on Wednesday, 02-25-26 2:00PM in House conference room 325 VIA VIDEOCONFERENCE.",
      "chamber": "H"
    },
    {
      "date": "2026-02-25",
      "action": "The committee on JHA recommend that the measure be PASSED, WITH AMENDMENTS. The votes were as follows: 9 Ayes: Representative(s) Tarnas, Poepoe, Cochran, Hashem, Kahaloa, Sayama, Takayama, Garcia, Shimizu; Ayes with reservations: none; 0 Noes: none; and 1 Excused: Representative(s) Belatti.",
      "chamber": "H"
    },
    {
      "date": "2026-03-06",
      "action": "Reported from JHA (Stand. Com. Rep. No. 1142-26) as amended in HD 2, recommending passage on Third Reading.",
      "chamber": "H"
    },
    {
      "date": "2026-03-06",
      "action": "Forty-eight (48) hours notice Tuesday, 03-10-26.",
      "chamber": "H"
    },
    {
      "date": "2026-03-10",
      "action": "Passed Third Reading as amended in HD 2 with Representative(s) Kila, Kitagawa, Olds, Sayama voting aye with reservations; Representative(s) Matayoshi, Pierick voting no (2) and none excused (0). Transmitted to Senate.",
      "chamber": "H"
    },
    {
      "date": "2026-03-12",
      "action": "Received from House (Hse. Com. No. 252).",
      "chamber": "S"
    },
    {
      "date": "2026-03-12",
      "action": "Passed First Reading.",
      "chamber": "S"
    },
    {
      "date": "2026-03-12",
      "action": "Referred to PSM, JDC/WAM.",
      "chamber": "S"
    }
  ],
  "votes": [],
  "texts": [
    {
      "date": "2026-01-20",
      "type": "Introduced",
      "url": "https://www.capitol.hawaii.gov/sessions/session2026/bills/HB1628_.HTM",
      "doc_id": 3325236
    },
    {
      "date": "2026-02-19",
      "type": "Amended",
      "url": "https://www.capitol.hawaii.gov/sessions/session2026/bills/HB1628_HD1_.HTM",
      "doc_id": 3368993
    },
    {
      "date": "2026-03-07",
      "type": "Amended",
      "url": "https://www.capitol.hawaii.gov/sessions/session2026/bills/HB1628_HD2_.HTM",
      "doc_id": 3388017
    }
  ],
  "committee": {
    "committee_id": 2793,
    "chamber": "S",
    "chamber_id": 32,
    "name": "Public Safety, Intergovernmental and Military Affairs"
  },
  "subjects": [
    "Hawaii Paroling Authority",
    "Department of Corrections and Rehabilitation",
    "Compassionate Release",
    "Working Group"
  ]
}