{
  "id": 2117682,
  "state": "UT",
  "state_name": "Utah",
  "bill_number": "HB0576",
  "title": "Child Welfare Timeline Compliance Amendments",
  "summary": "Child Welfare Timeline Compliance Amendments",
  "status": "dead",
  "status_label": "Failed",
  "status_code": 6,
  "categories": [
    "education"
  ],
  "primary_category": "education",
  "level": "state",
  "last_action_date": "",
  "last_action": "",
  "url": "https://legiscan.com/UT/bill/HB0576/2026",
  "legiscan_url": "https://legiscan.com/UT/bill/HB0576/2026",
  "state_url": "https://le.utah.gov/~2026/bills/static/HB0576.html",
  "sponsors": [
    "Candice Pierucci (R) [Rep]"
  ],
  "introduced_date": "2026-03-06",
  "session": "2026 General Session",
  "actions": [
    {
      "date": "2026-02-16",
      "action": "Bill Numbered but not Distributed in Legislative Research and General Counsel",
      "chamber": ""
    },
    {
      "date": "2026-02-16",
      "action": "Numbered Bill Publicly Distributed in Legislative Research and General Counsel",
      "chamber": ""
    },
    {
      "date": "2026-02-16",
      "action": "LFA/ bill assigned to staff for fiscal analysis for HB0576 in Legislative Fiscal Analyst",
      "chamber": ""
    },
    {
      "date": "2026-02-16",
      "action": "LFA/ bill sent to agencies for fiscal input for HB0576 in Legislative Fiscal Agency",
      "chamber": ""
    },
    {
      "date": "2026-02-17",
      "action": "House/ received bill from Legislative Research in Clerk of the House",
      "chamber": "H"
    },
    {
      "date": "2026-02-17",
      "action": "House/ 1st reading (Introduced) in House Rules Committee",
      "chamber": "H"
    },
    {
      "date": "2026-02-18",
      "action": "LFA/ fiscal note sent to sponsor for HB0576 in Version Sponsor",
      "chamber": ""
    },
    {
      "date": "2026-02-18",
      "action": "LFA/ fiscal note publicly available for HB0576 in Released",
      "chamber": ""
    },
    {
      "date": "2026-02-18",
      "action": "House/ received fiscal note from Fiscal Analyst in House Rules Committee",
      "chamber": "H"
    },
    {
      "date": "2026-02-19",
      "action": "House/ to standing committee in House Judiciary Committee",
      "chamber": "H"
    },
    {
      "date": "2026-03-02",
      "action": "House Comm - Not Considered in House Judiciary Committee",
      "chamber": "H"
    },
    {
      "date": "2026-03-03",
      "action": "House Comm - Recommends Returned to Rules in House Judiciary Committee",
      "chamber": "H"
    },
    {
      "date": "2026-03-05",
      "action": "House/ comm rpt/ sent to Rules in House Rules Committee",
      "chamber": "H"
    },
    {
      "date": "2026-03-06",
      "action": "House/ strike enacting clause in Clerk of the House",
      "chamber": "H"
    },
    {
      "date": "2026-03-06",
      "action": "House/ filed in House file for bills not passed",
      "chamber": "H"
    }
  ],
  "votes": [],
  "texts": [
    {
      "date": "2026-02-16",
      "type": "Introduced",
      "url": "https://le.utah.gov/Session/2026/bills/introduced/HB0576.pdf",
      "doc_id": 3363891
    }
  ],
  "committee": [],
  "subjects": [
    "Health and Human Services",
    "Child Welfare",
    "Judicial Administration",
    "Courts",
    "Judicial Operations"
  ]
}