{
  "id": 2121628,
  "state": "CA",
  "state_name": "California",
  "bill_number": "AB2551",
  "title": "Behavioral health care coverage.",
  "summary": "An act relating to health care coverage.",
  "status": "introduced",
  "status_label": "Introduced",
  "status_code": 1,
  "categories": [
    "healthcare"
  ],
  "primary_category": "healthcare",
  "level": "state",
  "last_action_date": "",
  "last_action": "",
  "url": "https://legiscan.com/CA/bill/AB2551/2025",
  "legiscan_url": "https://legiscan.com/CA/bill/AB2551/2025",
  "state_url": "https://leginfo.legislature.ca.gov/faces/billStatusClient.xhtml?bill_id=202520260AB2551",
  "sponsors": [
    "Sade Elhawary (D) [Rep]"
  ],
  "introduced_date": "2026-02-20",
  "session": "2025-2026 Regular Session",
  "actions": [
    {
      "date": "2026-02-20",
      "action": "Read first time. To print.",
      "chamber": "A"
    },
    {
      "date": "2026-02-21",
      "action": "From printer. May be heard in committee March 23.",
      "chamber": "A"
    }
  ],
  "votes": [],
  "texts": [
    {
      "date": "2026-02-20",
      "type": "Introduced",
      "url": "https://leginfo.legislature.ca.gov/faces/billTextClient.xhtml?bill_id=202520260AB2551#99INT",
      "doc_id": 3371170
    }
  ],
  "committee": [],
  "subjects": []
}